NeoNMM/Scrypt2.py
NeoNMM/Scrypt_3node.py
NeoNMM/Scrypt_interictal_to_seizure.py
NeoNMM/Scrypt_single_node.py
NeoNMM/__init__.py
NeoNMM/PackageSources/__init__.py
NeoNMM/PackageSources/Computation/Classes.py
NeoNMM/PackageSources/Computation/Filter.py
NeoNMM/PackageSources/Computation/Generate_Signal.py
NeoNMM/PackageSources/Computation/Loading.py
NeoNMM/PackageSources/Computation/__init__.py
NeoNMM/PackageSources/Display/EEG_Viewer.py
NeoNMM/PackageSources/Display/Mesh3DView.py
NeoNMM/PackageSources/Display/Spectrogram.py
NeoNMM/PackageSources/Display/__init__.py
NeoNMM/PackageSources/Model/Cortex_Model_NeoNMM.py
NeoNMM/PackageSources/Model/Model_NeoNMM.py
NeoNMM/PackageSources/Model/Model_NeoNMM_GUI.py
NeoNMM/PackageSources/Model/__init__.py
NeoNMM-2.7.dist-info/LICENSE
NeoNMM-2.7.dist-info/METADATA
NeoNMM-2.7.dist-info/WHEEL
NeoNMM-2.7.dist-info/top_level.txt
NeoNMM-2.7.dist-info/RECORD
