Metadata-Version: 2.1
Name: NeoNMM
Version: 2.7
Summary: NeoNMM is a software package for simulating mesoscale (neuronal population) and macroscale (connected neuronal populations at the whole brain level)
Author: Maxime Yochum
Author-email: MAxime Yochum <maxime.yochum@univ-rennes.fr>
Project-URL: Homepage, https://github.com/ymmx2/NeoNMM
Project-URL: Issues, https://github.com/ymmx2/NeoNMM/issues
Classifier: Programming Language :: Python :: 3
Classifier: License :: OSI Approved :: GNU General Public License v3 (GPLv3)
Classifier: Operating System :: OS Independent
Requires-Python: >=3.8
License-File: LICENSE
